CHANGES
DOKKU_SCALE
LICENSE
MANIFEST.in
Procfile
README.md
requirements.txt
runtime.txt
setup.py
scrapymon/__init__.py
scrapymon/__main__.py
scrapymon/app.py
scrapymon.egg-info/PKG-INFO
scrapymon.egg-info/SOURCES.txt
scrapymon.egg-info/dependency_links.txt
scrapymon.egg-info/entry_points.txt
scrapymon.egg-info/requires.txt
scrapymon.egg-info/top_level.txt
scrapymon/config/__init__.py
scrapymon/config/default.py
scrapymon/static/base.css
scrapymon/static/base.js
scrapymon/static/flat-ui/css/flat-ui.css
scrapymon/static/flat-ui/css/flat-ui.css.map
scrapymon/static/flat-ui/css/flat-ui.min.css
scrapymon/static/flat-ui/fonts/glyphicons/flat-ui-icons-regular.eot
scrapymon/static/flat-ui/fonts/glyphicons/flat-ui-icons-regular.svg
scrapymon/static/flat-ui/fonts/glyphicons/flat-ui-icons-regular.ttf
scrapymon/static/flat-ui/fonts/glyphicons/flat-ui-icons-regular.woff
scrapymon/static/flat-ui/fonts/glyphicons/selection.json
scrapymon/static/flat-ui/fonts/lato/lato-black.eot
scrapymon/static/flat-ui/fonts/lato/lato-black.svg
scrapymon/static/flat-ui/fonts/lato/lato-black.ttf
scrapymon/static/flat-ui/fonts/lato/lato-black.woff
scrapymon/static/flat-ui/fonts/lato/lato-bold.eot
scrapymon/static/flat-ui/fonts/lato/lato-bold.svg
scrapymon/static/flat-ui/fonts/lato/lato-bold.ttf
scrapymon/static/flat-ui/fonts/lato/lato-bold.woff
scrapymon/static/flat-ui/fonts/lato/lato-bolditalic.eot
scrapymon/static/flat-ui/fonts/lato/lato-bolditalic.svg
scrapymon/static/flat-ui/fonts/lato/lato-bolditalic.ttf
scrapymon/static/flat-ui/fonts/lato/lato-bolditalic.woff
scrapymon/static/flat-ui/fonts/lato/lato-italic.eot
scrapymon/static/flat-ui/fonts/lato/lato-italic.svg
scrapymon/static/flat-ui/fonts/lato/lato-italic.ttf
scrapymon/static/flat-ui/fonts/lato/lato-italic.woff
scrapymon/static/flat-ui/fonts/lato/lato-light.eot
scrapymon/static/flat-ui/fonts/lato/lato-light.svg
scrapymon/static/flat-ui/fonts/lato/lato-light.ttf
scrapymon/static/flat-ui/fonts/lato/lato-light.woff
scrapymon/static/flat-ui/fonts/lato/lato-regular.eot
scrapymon/static/flat-ui/fonts/lato/lato-regular.svg
scrapymon/static/flat-ui/fonts/lato/lato-regular.ttf
scrapymon/static/flat-ui/fonts/lato/lato-regular.woff
