Metadata-Version: 1.1
Name: scrapymon
Version: 0.1.0
Summary: Simple management UI for scrapyd
Home-page: https://github.com/jxltom/scrapymon/
Author: jxltom
Author-email: jxltom@gmail.com
License: MIT
Platform: UNKNOWN
Classifier: Development Status :: 4 - Beta
Classifier: License :: OSI Approved :: MIT License
Classifier: Operating System :: OS Independent
Classifier: Programming Language :: Python :: 3
